Core/Anlyst.py
Core/NetWork.py
Core/URLs.py
Core/Writer.py
Core/__init__.py
Task/BigTask.py
Task/NetworkTask.py
Task/Task.py
Task/TaskManger.py
Task/TaskMessage.py
Task/__init__.py
TaskSpider-0.0.3.dist-info/LICENSE
TaskSpider-0.0.3.dist-info/METADATA
TaskSpider-0.0.3.dist-info/WHEEL
TaskSpider-0.0.3.dist-info/top_level.txt
TaskSpider-0.0.3.dist-info/RECORD
