Metadata-Version: 2.1
Name: TaskSpider
Version: 0.0.3
Summary: A framework which can help you make your webspider more OOP and easy
Home-page: https://github.com/WuYuMax/TaskSpider
Author: WuYuMax
Author-email: 332062922@qq.com
License: UNKNOWN
Platform: UNKNOWN
Classifier: Programming Language :: Python :: 3
Classifier: License :: OSI Approved :: Apache Software License
Classifier: Operating System :: OS Independent
